termella/__init__.py
termella/ansi.py
termella/app.py
termella/core.py
termella/live.py
termella/markup.py
termella/printer.py
termella/renderer.py
termella/widgets.py
termella/input/__init__.py
termella/input/listener.py
termella/input/win_input.py
termella/ui/__init__.py
termella/ui/box.py
termella/ui/core.py
termella/ui/input.py
termella/ui/screen.py
termella/ui/text.py
termella/widgets/__init__.py
termella/widgets/bars.py
termella/widgets/base.py
termella/widgets/layouts.py
termella/widgets/menus.py
termella/widgets/spinner.py
termella/widgets/tables.py
termella/widgets/tree.py
termella-0.0.9.dist-info/licenses/LICENSE
termella-0.0.9.dist-info/METADATA
termella-0.0.9.dist-info/WHEEL
termella-0.0.9.dist-info/top_level.txt
termella-0.0.9.dist-info/RECORD
