Metadata-Version: 2.4
Name: termella
Version: 0.0.9
Summary: A Python library for rich text and beautiful formatting in the terminal.
Home-page: https://github.com/codewithzaqar/termella
Author: codewithzaqar
Author-email: your.email@example.com
License: MIT
Project-URL: Bug Tracker, https://github.com/codewithzaqar/termella/issues
Project-URL: Source, https://github.com/codewithzaqar/termella
Keywords: terminal,cli,colors,ansi,rich-text,formatting,ui,console
Classifier: Development Status :: 4 - Beta
Classifier: Intended Audience :: Developers
Classifier: Environment :: Console
Classifier: License :: OSI Approved :: MIT License
Classifier: Operating System :: OS Independent
Classifier: Programming Language :: Python :: 3
Classifier: Programming Language :: Python :: 3.6
Classifier: Programming Language :: Python :: 3.7
Classifier: Programming Language :: Python :: 3.8
Classifier: Programming Language :: Python :: 3.9
Classifier: Programming Language :: Python :: 3.10
Classifier: Topic :: Software Development :: Libraries :: Python Modules
Classifier: Topic :: Terminals
Classifier: Topic :: Utilities
Requires-Python: >=3.6
License-File: LICENSE
Dynamic: author
Dynamic: author-email
Dynamic: classifier
Dynamic: description
Dynamic: description-content-type
Dynamic: home-page
Dynamic: keywords
Dynamic: license
Dynamic: license-file
Dynamic: project-url
Dynamic: requires-python
Dynamic: summary
